plaid_old/__init__.py
plaid_old/client.py
plaid_old/errors.py
plaid_old/requester.py
plaid_old/utils.py
plaid_old/version.py
plaid_old/api/__init__.py
plaid_old/api/accounts.py
plaid_old/api/api.py
plaid_old/api/assets.py
plaid_old/api/auth.py
plaid_old/api/categories.py
plaid_old/api/credit_details.py
plaid_old/api/identity.py
plaid_old/api/income.py
plaid_old/api/institutions.py
plaid_old/api/item.py
plaid_old/api/processor.py
plaid_old/api/sandbox.py
plaid_old/api/transactions.py
tests/__init__.py
tests/integration/__init__.py
tests/integration/test_accounts.py
tests/integration/test_assets.py
tests/integration/test_auth.py
tests/integration/test_categories.py
tests/integration/test_credit_details.py
tests/integration/test_identity.py
tests/integration/test_income.py
tests/integration/test_institutions.py
tests/integration/test_item.py
tests/integration/test_processor.py
tests/integration/test_transactions.py
tests/integration/util.py
tests/unit/__init__.py
tests/unit/test_errors.py
plaid_python_old-2.3.3.dist-info/LICENSE
plaid_python_old-2.3.3.dist-info/METADATA
plaid_python_old-2.3.3.dist-info/WHEEL
plaid_python_old-2.3.3.dist-info/top_level.txt
plaid_python_old-2.3.3.dist-info/RECORD
