Metadata-Version: 2.1
Name: plaid-python-old
Version: 2.3.3
Summary: Python client library for the Plaid API and Link
Home-page: https://github.com/plaid/plaid-python
Download-URL: https://github.com/plaid/plaid-python/tarball/v2.3.3
Author: Plaid Technologies
Author-email: developers@plaid.com
License: MIT
Keywords: api,client,plaid
Classifier: Programming Language :: Python
Classifier: Programming Language :: Python :: 2
Classifier: Programming Language :: Python :: 2.7
Classifier: Programming Language :: Python :: 3
Classifier: Programming Language :: Python :: 3.4
Classifier: Programming Language :: Python :: 3.5
Classifier: Programming Language :: Python :: 3.6
Classifier: Topic :: Software Development :: Libraries :: Python Modules
Classifier: Environment :: Web Environment
License-File: LICENSE
Requires-Dist: requests (>=2.7.0)
